sqs_polling/__init__.py
sqs_polling/__version__.py
sqs_polling/sqs_polling.py
sqs_polling/tests/__init__.py
sqs_polling/tests/test_sqs_polling.py
sqs_polling-0.1.0.dist-info/METADATA
sqs_polling-0.1.0.dist-info/WHEEL
sqs_polling-0.1.0.dist-info/top_level.txt
sqs_polling-0.1.0.dist-info/RECORD
