Metadata-Version: 2.1
Name: sqs-polling
Version: 0.1.0
Summary: Polls AWS SQS messages and executes your callback.
Home-page: https://github.com/ohke/sqs-polling
Author: Kenta Onishi
Author-email: ohke.develop@gmail.com
License: UNKNOWN
Platform: UNKNOWN
Classifier: Development Status :: 4 - Beta
Classifier: Intended Audience :: Developers
Classifier: Topic :: Software Development :: Libraries :: Python Modules
Classifier: License :: OSI Approved :: MIT License
Classifier: Operating System :: OS Independent
Classifier: Programming Language :: Python :: 3
Classifier: Programming Language :: Python :: 3.5
Classifier: Programming Language :: Python :: 3.6
Classifier: Programming Language :: Python :: 3.7
Classifier: Programming Language :: Python :: 3.8
Requires-Python: ~=3.5
Requires-Dist: boto3
